<annotation>
	<folder>jpgimg</folder>
	<filename>Pomacanthus_imperator_0016.jpg</filename>
	<path>F:\jpgimg\Pomacanthus_imperator_0016.jpg</path>
	<source>
		<database>Unknown</database>
	</source>
	<size>
		<width>632</width>
		<height>470</height>
		<depth>3</depth>
	</size>
	<segmented>0</segmented>
	<object>
		<name>Pomacanthus_imperator</name>
		<pose>Unspecified</pose>
		<truncated>0</truncated>
		<difficult>0</difficult>
		<bndbox>
			<xmin>3</xmin>
			<ymin>8</ymin>
			<xmax>622</xmax>
			<ymax>457</ymax>
		</bndbox>
	</object>
</annotation>
